{
  "updated": "2026-03-03T02:27:34.161Z",
  "auto_fetched": true,
  "xrp": {
    "price": 1.38,
    "change_24h": 1.3202118781809613,
    "volume_24h": 3587271193.332408,
    "market_cap": 84208812717.32155,
    "data_date": "2026-03-03",
    "source": "coingecko"
  },
  "rlusd": {
    "market_cap": 1583579199.6000812,
    "data_date": "2026-03-03",
    "source": "coingecko"
  },
  "macro": {
    "usd_jpy": {
      "value": 157.45,
      "data_date": "2026-03-02",
      "source": "frankfurter"
    },
    "jpn_10y": 2.24,
    "us_10y_yield": {
      "value": 3.97,
      "data_date": "2026-02-27",
      "source": "fred"
    },
    "brent_crude": {
      "value": 71.9,
      "data_date": "2026-02-23",
      "source": "fred"
    },
    "dxy": {
      "value": null,
      "data_date": null,
      "source": "twelve_data"
    },
    "sp500": {
      "value": 0.094999999,
      "data_date": "2026-03-02",
      "source": "twelve_data"
    },
    "fear_greed": {
      "value": 14,
      "label": "Extreme Fear",
      "data_date": "2026-03-03",
      "source": "alternative.me"
    }
  },
  "manual": {
    "odl_volume_annualized": null,
    "xrp_etf_aum": null,
    "rlusd_circulation": null,
    "permissioned_dex_institutions": null,
    "clarity_act_status": "Pending",
    "_last_manual_update": null
  },
  "kill_switches": {
    "odl_volume": {
      "target": 25000000000,
      "current": null,
      "deadline": "2026-12-31",
      "status": "NEEDS_DATA",
      "pct_complete": null
    },
    "rlusd_circulation": {
      "target": 5000000000,
      "current": 1583579199.6000812,
      "deadline": "2026-12-31",
      "status": "TRACKING",
      "pct_complete": 32
    },
    "xrp_etf_aum": {
      "target": 5000000000,
      "current": null,
      "deadline": "2026-12-31",
      "status": "NEEDS_DATA",
      "pct_complete": null
    },
    "permissioned_dex_adoption": {
      "target_institutions": 5,
      "current": null,
      "deadline": "2026-09-30",
      "status": "NEEDS_DATA"
    },
    "clarity_act": {
      "target": "passed_or_advanced",
      "current": "pending",
      "deadline": "2026-12-31",
      "status": "PENDING"
    }
  },
  "thesis_scores": {
    "regulatory": {
      "status": "CONFIRMED",
      "confidence": "high"
    },
    "institutional_custody": {
      "status": "STRONG",
      "confidence": "high"
    },
    "etf_adoption": {
      "status": "CONFIRMED — MONITOR FLOWS",
      "confidence": "high"
    },
    "xrpl_infrastructure": {
      "status": "ACCELERATING",
      "confidence": "high"
    },
    "stablecoin_adoption": {
      "status": "STALLING — CONTRACTION DETECTED",
      "confidence": "medium"
    },
    "odl_volume": {
      "status": "NEEDS_DATA",
      "confidence": "low"
    },
    "japan_adoption": {
      "status": "FAVORABLE — MONITORING",
      "confidence": "medium"
    },
    "macro_environment": {
      "status": "STRESSED — ELEVATED",
      "confidence": "medium"
    }
  },
  "probability": {
    "bear": 12,
    "base": 42,
    "mid": 34,
    "bull": 12,
    "last_updated": "2026-03-03T02:38:20.324Z",
    "last_reasoning": "Shifting 2% from base to bear and 2% from base to mid. Bear increase reflects: XRP at $1.38 (well below $2 base floor), extreme fear at 14, compound stress pre-loaded, multiple data feeds degraded. Mid increase reflects: RLUSD recovery to $1.584B, institutional infrastructure buildout continuing (PermissionedDEX live, Ripple Prime, Metallicus FedNow), 7 ETFs operational. The thesis infrastructure is advancing while market conditions deteriorate — this divergence justifies widening the distribution rather than collapsing toward bear."
  },
  "bear_case": {
    "counter_thesis_score": 52,
    "score_reasoning": "Elevated from baseline due to: XRP trading 31% below base case floor, extreme fear environment, 3 of 5 automated kill switches lacking data, zero PermissionedDEX adoption after 11 days live, and compound macro stress pre-loaded. Thesis infrastructure is advancing but the market is not validating it, and key metrics remain unverifiable.",
    "competing_infrastructure": [
      {
        "name": "SWIFT GPI",
        "status": "MONITORING",
        "status_text": "SWIFT continues incremental upgrades to GPI tracking and pre-validation. 11,500-bank network effects remain the strongest competitive moat. No XRPL integration announced."
      },
      {
        "name": "Visa B2B Connect",
        "status": "MONITORING",
        "status_text": "Visa B2B Connect operational across 100+ countries. Enterprise adoption steady. Competes directly for the same cross-border settlement corridors XRP targets."
      },
      {
        "name": "JPMorgan Kinexys",
        "status": "ELEVATED_RISK",
        "status_text": "Kinexys (formerly Onyx) processing $2B+/day in institutional transfers. JPMorgan's balance sheet and client base give it distribution advantages Ripple cannot match. Ripple Prime paper explicitly positions against JPMorgan — acknowledges the threat."
      },
      {
        "name": "BIS Project Nexus",
        "status": "MONITORING",
        "status_text": "Multi-central-bank initiative to interlink domestic fast payment systems. If successful, could eliminate the need for bridge currencies entirely. Kill Switch #9 tracks this. No live deployment yet but political backing is strong."
      },
      {
        "name": "Ethereum Institutional",
        "status": "MONITORING",
        "status_text": "Ethereum L2 ecosystem expanding institutional DeFi. BlackRock BUIDL fund on Ethereum. However, settlement speed and cost still favor XRPL for high-frequency cross-border use cases."
      }
    ],
    "odl_stagnation": "ODL volume data has been unavailable for an extended period — Ripple's decision to stop publishing this data is itself a bearish signal. Without volume proof, the core utility thesis remains an assertion, not a measurement.",
    "token_velocity_concern": "Token velocity data (Kill Switch #8) remains UNKNOWN. If XRP functions purely as a bridge asset with sub-second hold times, value capture for token holders may be minimal regardless of volume growth. This is the most underexamined bear thesis dimension.",
    "macro_headwinds": [
      {
        "name": "Global Recession Risk",
        "status": "ELEVATED_RISK",
        "status_text": "Fear & Greed at 14, compound macro stress pre-loaded, S&P data anomalous but likely declining. Trade war via Section 122 tariffs actively depressing global growth expectations."
      },
      {
        "name": "Crypto Winter Signals",
        "status": "MONITORING",
        "status_text": "XRP at $1.38 down significantly from recent highs. Extreme fear readings. However, institutional infrastructure buildout (ETFs, PermissionedDEX, Ripple Prime) is counter-cyclical — not typical of crypto winter capitulation."
      },
      {
        "name": "Regulatory Reversal Risk",
        "status": "LOW_RISK",
        "status_text": "Clarity Act pending but SEC/CFTC regulatory posture remains favorable. 7 ETFs approved and operational. No reversal signals detected."
      },
      {
        "name": "Rate Hike Extension",
        "status": "MONITORING",
        "status_text": "US 10Y at 3.97% suggests markets pricing some easing. However, BOJ tightening risk is the more relevant rate threat — a BOJ hike compresses the carry trade, triggering global liquidity withdrawal that would pressure all risk assets including XRP."
      }
    ],
    "bear_narrative": "Bear pressure at 52 — thesis underwater but not drowning. Three kill switches at WARNING: ODL volume data classified as SUSPICIOUS_ABSENCE with behavioral evidence suggesting Ripple is pivoting from XRP bridge asset to diversified infrastructure provider; RLUSD stalling at $1.58B needing $11.28M/day to hit target with no visible catalyst; and the ODL transparency kill switch may not be met on its original terms because the product has evolved beyond XRP-specific metrics. The infrastructure story is real — live ETFs, multi-regulator registrations, SBI's ¥10B bonds, record on-chain activity — but the volume story that would convert infrastructure into thesis confirmation remains a black box. Compound stress is pre-loaded with all three legs deteriorating toward elevated simultaneously; one external shock (Hormuz, BOJ surprise) could cascade the macro environment from orderly to disorderly. The paradox holds: the conditions that would most stress this position are the same conditions that most validate the need for alternative settlement infrastructure. INCREASE_MONITORING with Q2 2026 as the next decision gate — if RLUSD doesn't accelerate and ODL data doesn't surface, the recommendation hardens.",
    "last_updated": "2026-03-03T02:38:20.324Z"
  },
  "last_analysis": {
    "timestamp": "2026-03-03T02:38:20.324Z",
    "run_type": "evening",
    "stress_level": "ELEVATED",
    "stress_score": 62,
    "applied_at": "2026-03-03T02:39:48.173Z",
    "changes_applied": 2
  }
}